protosaurus-0.3.2.dist-info/METADATA
protosaurus-0.3.2.dist-info/WHEEL
protosaurus-0.3.2.dist-info/RECORD
protosaurus-0.3.2.dist-info/entry_points.txt
protosaurus-0.3.2.dist-info/licenses/LICENSE
protosaurus/cli.py
protosaurus/protosaurus_ext.cpython-310-x86_64-linux-gnu.so
protosaurus/__init__.py
