Metadata-Version: 2.1
Name: protosaurus
Version: 0.3.2
Summary: Protocol Buffers at runtime
Author-Email: Thomas Oberbichler <thomas.oberbichler@gmail.com>
Classifier: License :: OSI Approved :: ISC License (ISCL)
Project-URL: Homepage, https://github.com/oberbichler/protosaurus
Requires-Python: >=3.8
Requires-Dist: click>=8.1
Requires-Dist: requests>=2.31
Requires-Dist: pytest>=6.0; extra == "test"
Requires-Dist: deepdiff; extra == "test"
Provides-Extra: test
License-File: LICENSE
